chromahacker/.DS_Store
chromahacker/__init__.py
chromahacker/apply.py
chromahacker/color_input.py
chromahacker/colorschemes/__init__.py
chromahacker/colorschemes/colorschemes.py
chromahacker/greyscale.py
chromahacker/id_clut.py
chromahacker/palettize.py
chromahacker/process_image.py
chromahacker/spline.py
chromahacker-0.3.6.dist-info/METADATA
chromahacker-0.3.6.dist-info/WHEEL
chromahacker-0.3.6.dist-info/entry_points.txt
chromahacker-0.3.6.dist-info/RECORD
